Workbook

Sheet Resumen
A1: CFA Nivel 2 – Panel de control
A2: Celdas amarillas con texto azul = las editas tú. El resto se calcula solo.
A4: Inicio del plan (lunes semana 1) | B4: 46321 | C4: Dato tuyo: hoy es 26-oct-2026
A5: Fecha del examen | B5: 46522 | C5: SUPUESTO (mediados de mayo): confirmar y cambiar
A6: Hoy | B6: =TODAY() -> 46321
A7: Semana actual del plan | B7: =MAX(1,MIN(29,INT((B6-B4)/7)+1)) -> 1
A8: Semanas que faltan para el examen | B8: =MAX(0,INT((B5-B6)/7)) -> 28
A9: Minutos por bloque | B9: 90 | C9: 2 pomodoros de 40 min + 5 min de pausa; celular fuera de la pieza
A10: Bloques ideales por semana | B10: 10 | C10: Mar–Jue noche 4, Vie 2, Sáb 2, Dom 2
A11: Bloques mínimos por semana | B11: 7 | C11: Bajo esto, solo núcleo (leer/ejercicios) y errores
A12: Deuda que obliga a correr el calendario | B12: 6 | C12: Regla: > 6 bloques de deuda = correr 1 semana
A13: Máx. bloques de deuda recuperables por semana | B13: 3 | C13: Con transporte, sábado largo o domingo libre
A14: Horas por bloque | B14: =B9/60 -> 1.5
A16: Avance acumulado
A17: Bloques planeados (semanas ya registradas) | B17: =SUMPRODUCT((Calendario!$H$5:$H$33<>"")*Calendario!$G$5:$G$33) -> 0
A18: Bloques hechos | B18: =SUM(Calendario!$H$5:$H$33) -> 0
A19: Deuda actual de bloques | B19: =MAX(0,B17-B18) -> 0
A20: Horas de estudio acumuladas | B20: =B18*B14 -> 0
A21: Cumplimiento acumulado | B21: =IF(B17=0,"",B18/B17)
A22: Estado | B22: =IF(B17=0,"Sin datos aún",IF(B19>B12,"CORRER CALENDARIO",IF(B19>3,"ALERTA","EN RUTA"))) -> Sin datos aún
A24: Mensaje
A25: =IF(B22="CORRER CALENDARIO","Estás corriendo el calendario. Séneca: «No es que tengamos poco tiempo, sino que perdemos mucho». Cada bloque perdido es potencial que se queda sin usar: la charter te abre FP&A senior, riesgo, portafolio. Hoy mismo recuperas 2 bloques y me avisas.",IF(B22="ALERTA","Vas atrasado, todavía a tiempo. Marco Aurelio: «Lo que se interpone en el camino se convierte en el camino». Recupera esta semana hasta 3 bloques y no sacrifiques los de núcleo.",IF(B22="EN RUTA","En ruta. La disciplina de hoy es la libertad de tu yo de mayo. Sigue el plan, sin heroísmos.","Parte registrando la semana 1 en Calendario."))) -> Parte registrando la semana 1 en Calendario.

Sheet Semana tipo
A1: Semana tipo (10 bloques de 90 min)
A2: Bloque = 2 pomodoros (40' foco + 5' pausa). Transporte = lectura/subrayado en papel, sentado; es extra y no cuenta como bloque.
A4: Día | B4: Franja | C4: Dónde | D4: Bloque(s) | E4: Qué hacer | F4: Nº bloques
A5: Lunes | B5: 06:45–08:00 / 17:30–18:30 | C5: Transporte | D5: T (lectura) | E5: Leer y subrayar con lápiz en el libro Schweser del tema actual | F5: 0
A6: Lunes | B6: 20:00–21:30 | C6: Casa (escritorio CFA) | D6: R | E6: Resumir lo subrayado del transporte (tope ~8–10 págs por tema) | F6: 1
A7: Martes | B7: 06:45–08:00 / 17:30–18:30 | C7: Transporte | D7: T (lectura) | E7: Leer y subrayar | F7: 0
A8: Martes | B8: 20:00–21:30 | C8: Casa | D8: R | E8: Seguir resumiendo + fórmulas con calculadora BA II Plus | F8: 1
A9: Miércoles | B9: 06:45–08:00 / 17:30–18:30 | C9: Transporte | D9: T (lectura) | E9: Leer y subrayar | F9: 0
A10: Miércoles | B10: 20:00–21:30 | C10: Casa | D10: Q | E10: Ejercicios del tema (vignettes) + registro de errores | F10: 1
A11: Jueves | B11: 06:45–08:00 / 17:30–18:30 | C11: Transporte | D11: T (lectura) | E11: Leer y subrayar | F11: 0
A12: Jueves | B12: 20:00–21:30 | C12: Casa | D12: Q | E12: Ejercicios + Simulador de errores; cerrar la semana de errores | F12: 1
A13: Viernes | B13: 15:00–18:30 | C13: Casa | D13: L + Q | E13: Bloque fuerte (Samexid opcional según tu médico): lo más difícil + ejercicios | F13: 2
A14: Viernes noche | B14: — | C14: Casa de tu polola | D14: — | E14: Descanso total | F14: 0
A15: Sábado | B15: 09:00–12:00 | C15: Casa de tu polola | D15: L + R | E15: Leer/subrayar lo pendiente + resumir | F15: 2
A16: Domingo | B16: 16:00–19:30 | C16: Casa | D16: V + F | E16: Repaso espaciado (errores + Ética 1 h) + Feynman / detector de brechas; planificar semana | F16: 2
E17: Total bloques / semana | F17: =SUM(F5:F16) -> 10
A19: Claves: L = leer y subrayar · R = resumir · Q = ejercicios + errores · V = repaso espaciado y Ética · F = Feynman / detector de brechas · T = transporte.
A20: Sueño: despertar 6:00. Tu rango actual (23:00–1:00) deja 5–7 h; apunta a acostarte antes de 23:30 entre semana.

Sheet Calendario
A1: Calendario de 29 semanas
A2: Escribe en 'Bloques plan' si cambia tu semana y en 'Bloques hechos' al cerrar el domingo. Deuda y estado se calculan solos.
A4: Sem | B4: Inicio (lun) | C4: Fin (dom) | D4: Tema | E4: Fase | F4: Colchón | G4: Bloques plan | H4: Bloques hechos | I4: Dif. | J4: Deuda acum. | K4: Cumpl. | L4: Estado | M4: Notas
A5: 1 | B5: =Resumen!$B$4+7*(A5-1) -> 46321 | C5: =B5+6 -> 46327 | D5: Quant | E5: Setup + 1ª pasada | F5: No | G5: 6 | I5: =IF(H5="","",H5-G5) | J5: =IF(H5="","",MAX(0,N(J4)+G5-H5)) | K5: =IF(OR(H5="",G5=0),"",H5/G5) | L5: =IF(H5="","Pendiente",IF(J5>Resumen!$B$12,"Correr calendario",IF(H5>=G5,"Cumplida",IF(H5>=Resumen!$B$11,"Parcial","Bajo mínimo")))) -> Pendiente | M5: Fin de semana 31-oct/1-nov = cumpleaños de tu polola (0 bloques Sáb/Dom). Setup: escritorio, calendario, diagnóstico y repaso L1 de Quant
A6: 2 | B6: =Resumen!$B$4+7*(A6-1) -> 46328 | C6: =B6+6 -> 46334 | D6: Quant | E6: 1ª pasada | F6: No | G6: 10 | I6: =IF(H6="","",H6-G6) | J6: =IF(H6="","",MAX(0,N(J5)+G6-H6)) | K6: =IF(OR(H6="",G6=0),"",H6/G6) | L6: =IF(H6="","Pendiente",IF(J6>Resumen!$B$12,"Correr calendario",IF(H6>=G6,"Cumplida",IF(H6>=Resumen!$B$11,"Parcial","Bajo mínimo")))) -> Pendiente
A7: 3 | B7: =Resumen!$B$4+7*(A7-1) -> 46335 | C7: =B7+6 -> 46341 | D7: Economía | E7: 1ª pasada | F7: No | G7: 10 | I7: =IF(H7="","",H7-G7) | J7: =IF(H7="","",MAX(0,N(J6)+G7-H7)) | K7: =IF(OR(H7="",G7=0),"",H7/G7) | L7: =IF(H7="","Pendiente",IF(J7>Resumen!$B$12,"Correr calendario",IF(H7>=G7,"Cumplida",IF(H7>=Resumen!$B$11,"Parcial","Bajo mínimo")))) -> Pendiente | M7: Tu tema más débil en el L1: repasa tu resumen L1 en el primer bloque
A8: 4 | B8: =Resumen!$B$4+7*(A8-1) -> 46342 | C8: =B8+6 -> 46348 | D8: Economía | E8: 1ª pasada | F8: No | G8: 10 | I8: =IF(H8="","",H8-G8) | J8: =IF(H8="","",MAX(0,N(J7)+G8-H8)) | K8: =IF(OR(H8="",G8=0),"",H8/G8) | L8: =IF(H8="","Pendiente",IF(J8>Resumen!$B$12,"Correr calendario",IF(H8>=G8,"Cumplida",IF(H8>=Resumen!$B$11,"Parcial","Bajo mínimo")))) -> Pendiente
A9: 5 | B9: =Resumen!$B$4+7*(A9-1) -> 46349 | C9: =B9+6 -> 46355 | D9: FSA | E9: 1ª pasada | F9: No | G9: 10 | I9: =IF(H9="","",H9-G9) | J9: =IF(H9="","",MAX(0,N(J8)+G9-H9)) | K9: =IF(OR(H9="",G9=0),"",H9/G9) | L9: =IF(H9="","Pendiente",IF(J9>Resumen!$B$12,"Correr calendario",IF(H9>=G9,"Cumplida",IF(H9>=Resumen!$B$11,"Parcial","Bajo mínimo")))) -> Pendiente
A10: 6 | B10: =Resumen!$B$4+7*(A10-1) -> 46356 | C10: =B10+6 -> 46362 | D10: FSA | E10: 1ª pasada | F10: No | G10: 8 | I10: =IF(H10="","",H10-G10) | J10: =IF(H10="","",MAX(0,N(J9)+G10-H10)) | K10: =IF(OR(H10="",G10=0),"",H10/G10) | L10: =IF(H10="","Pendiente",IF(J10>Resumen!$B$12,"Correr calendario",IF(H10>=G10,"Cumplida",IF(H10>=Resumen!$B$11,"Parcial","Bajo mínimo")))) -> Pendiente | M10: Matrimonio sáb 5-dic (−2 bloques), por confirmar
A11: 7 | B11: =Resumen!$B$4+7*(A11-1) -> 46363 | C11: =B11+6 -> 46369 | D11: FSA | E11: 1ª pasada | F11: No | G11: 8 | I11: =IF(H11="","",H11-G11) | J11: =IF(H11="","",MAX(0,N(J10)+G11-H11)) | K11: =IF(OR(H11="",G11=0),"",H11/G11) | L11: =IF(H11="","Pendiente",IF(J11>Resumen!$B$12,"Correr calendario",IF(H11>=G11,"Cumplida",IF(H11>=Resumen!$B$11,"Parcial","Bajo mínimo")))) -> Pendiente | M11: Matrimonio sáb 12-dic (−2 bloques), por confirmar. Mar 8-dic feriado (confirmar)
A12: 8 | B12: =Resumen!$B$4+7*(A12-1) -> 46370 | C12: =B12+6 -> 46376 | D12: Corporate Issuers | E12: 1ª pasada | F12: No | G12: 10 | I12: =IF(H12="","",H12-G12) | J12: =IF(H12="","",MAX(0,N(J11)+G12-H12)) | K12: =IF(OR(H12="",G12=0),"",H12/G12) | L12: =IF(H12="","Pendiente",IF(J12>Resumen!$B$12,"Correr calendario",IF(H12>=G12,"Cumplida",IF(H12>=Resumen!$B$11,"Parcial","Bajo mínimo")))) -> Pendiente
A13: 9 | B13: =Resumen!$B$4+7*(A13-1) -> 46377 | C13: =B13+6 -> 46383 | D13: Corporate Issuers | E13: 1ª pasada | F13: Sí | G13: 8 | I13: =IF(H13="","",H13-G13) | J13: =IF(H13="","",MAX(0,N(J12)+G13-H13)) | K13: =IF(OR(H13="",G13=0),"",H13/G13) | L13: =IF(H13="","Pendiente",IF(J13>Resumen!$B$12,"Correr calendario",IF(H13>=G13,"Cumplida",IF(H13>=Resumen!$B$11,"Parcial","Bajo mínimo")))) -> Pendiente | M13: Navidad (vie 25-dic): semana liviana, absorbe deuda
A14: 10 | B14: =Resumen!$B$4+7*(A14-1) -> 46384 | C14: =B14+6 -> 46390 | D14: Equity | E14: 1ª pasada | F14: No | G14: 8 | I14: =IF(H14="","",H14-G14) | J14: =IF(H14="","",MAX(0,N(J13)+G14-H14)) | K14: =IF(OR(H14="",G14=0),"",H14/G14) | L14: =IF(H14="","Pendiente",IF(J14>Resumen!$B$12,"Correr calendario",IF(H14>=G14,"Cumplida",IF(H14>=Resumen!$B$11,"Parcial","Bajo mínimo")))) -> Pendiente | M14: Año Nuevo: semana liviana
A15: 11 | B15: =Resumen!$B$4+7*(A15-1) -> 46391 | C15: =B15+6 -> 46397 | D15: Equity | E15: 1ª pasada | F15: No | G15: 10 | I15: =IF(H15="","",H15-G15) | J15: =IF(H15="","",MAX(0,N(J14)+G15-H15)) | K15: =IF(OR(H15="",G15=0),"",H15/G15) | L15: =IF(H15="","Pendiente",IF(J15>Resumen!$B$12,"Correr calendario",IF(H15>=G15,"Cumplida",IF(H15>=Resumen!$B$11,"Parcial","Bajo mínimo")))) -> Pendiente
A16: 12 | B16: =Resumen!$B$4+7*(A16-1) -> 46398 | C16: =B16+6 -> 46404 | D16: Equity | E16: 1ª pasada + chequeo | F16: Sí | G16: 10 | I16: =IF(H16="","",H16-G16) | J16: =IF(H16="","",MAX(0,N(J15)+G16-H16)) | K16: =IF(OR(H16="",G16=0),"",H16/G16) | L16: =IF(H16="","Pendiente",IF(J16>Resumen!$B$12,"Correr calendario",IF(H16>=G16,"Cumplida",IF(H16>=Resumen!$B$11,"Parcial","Bajo mínimo")))) -> Pendiente | M16: Chequeo intermedio: ¿Quant, Econ, FSA, CI y Equity ≥ 65%?
A17: 13 | B17: =Resumen!$B$4+7*(A17-1) -> 46405 | C17: =B17+6 -> 46411 | D17: Renta Fija | E17: 1ª pasada | F17: No | G17: 10 | I17: =IF(H17="","",H17-G17) | J17: =IF(H17="","",MAX(0,N(J16)+G17-H17)) | K17: =IF(OR(H17="",G17=0),"",H17/G17) | L17: =IF(H17="","Pendiente",IF(J17>Resumen!$B$12,"Correr calendario",IF(H17>=G17,"Cumplida",IF(H17>=Resumen!$B$11,"Parcial","Bajo mínimo")))) -> Pendiente
A18: 14 | B18: =Resumen!$B$4+7*(A18-1) -> 46412 | C18: =B18+6 -> 46418 | D18: Renta Fija | E18: 1ª pasada | F18: No | G18: 10 | I18: =IF(H18="","",H18-G18) | J18: =IF(H18="","",MAX(0,N(J17)+G18-H18)) | K18: =IF(OR(H18="",G18=0),"",H18/G18) | L18: =IF(H18="","Pendiente",IF(J18>Resumen!$B$12,"Correr calendario",IF(H18>=G18,"Cumplida",IF(H18>=Resumen!$B$11,"Parcial","Bajo mínimo")))) -> Pendiente
A19: 15 | B19: =Resumen!$B$4+7*(A19-1) -> 46419 | C19: =B19+6 -> 46425 | D19: Renta Fija | E19: 1ª pasada | F19: Sí | G19: 10 | I19: =IF(H19="","",H19-G19) | J19: =IF(H19="","",MAX(0,N(J18)+G19-H19)) | K19: =IF(OR(H19="",G19=0),"",H19/G19) | L19: =IF(H19="","Pendiente",IF(J19>Resumen!$B$12,"Correr calendario",IF(H19>=G19,"Cumplida",IF(H19>=Resumen!$B$11,"Parcial","Bajo mínimo")))) -> Pendiente | M19: Febrero: viaje con tu polola por definir (ajustar bloques de la semana que corresponda)
A20: 16 | B20: =Resumen!$B$4+7*(A20-1) -> 46426 | C20: =B20+6 -> 46432 | D20: Derivados | E20: 1ª pasada | F20: No | G20: 10 | I20: =IF(H20="","",H20-G20) | J20: =IF(H20="","",MAX(0,N(J19)+G20-H20)) | K20: =IF(OR(H20="",G20=0),"",H20/G20) | L20: =IF(H20="","Pendiente",IF(J20>Resumen!$B$12,"Correr calendario",IF(H20>=G20,"Cumplida",IF(H20>=Resumen!$B$11,"Parcial","Bajo mínimo")))) -> Pendiente | M20: Febrero: viaje por definir
A21: 17 | B21: =Resumen!$B$4+7*(A21-1) -> 46433 | C21: =B21+6 -> 46439 | D21: Derivados | E21: 1ª pasada | F21: No | G21: 10 | I21: =IF(H21="","",H21-G21) | J21: =IF(H21="","",MAX(0,N(J20)+G21-H21)) | K21: =IF(OR(H21="",G21=0),"",H21/G21) | L21: =IF(H21="","Pendiente",IF(J21>Resumen!$B$12,"Correr calendario",IF(H21>=G21,"Cumplida",IF(H21>=Resumen!$B$11,"Parcial","Bajo mínimo")))) -> Pendiente | M21: Febrero: viaje por definir
A22: 18 | B22: =Resumen!$B$4+7*(A22-1) -> 46440 | C22: =B22+6 -> 46446 | D22: Alternativos | E22: 1ª pasada | F22: No | G22: 10 | I22: =IF(H22="","",H22-G22) | J22: =IF(H22="","",MAX(0,N(J21)+G22-H22)) | K22: =IF(OR(H22="",G22=0),"",H22/G22) | L22: =IF(H22="","Pendiente",IF(J22>Resumen!$B$12,"Correr calendario",IF(H22>=G22,"Cumplida",IF(H22>=Resumen!$B$11,"Parcial","Bajo mínimo")))) -> Pendiente
A23: 19 | B23: =Resumen!$B$4+7*(A23-1) -> 46447 | C23: =B23+6 -> 46453 | D23: Alternativos | E23: 1ª pasada | F23: Sí | G23: 10 | I23: =IF(H23="","",H23-G23) | J23: =IF(H23="","",MAX(0,N(J22)+G23-H23)) | K23: =IF(OR(H23="",G23=0),"",H23/G23) | L23: =IF(H23="","Pendiente",IF(J23>Resumen!$B$12,"Correr calendario",IF(H23>=G23,"Cumplida",IF(H23>=Resumen!$B$11,"Parcial","Bajo mínimo")))) -> Pendiente
A24: 20 | B24: =Resumen!$B$4+7*(A24-1) -> 46454 | C24: =B24+6 -> 46460 | D24: Portafolio | E24: 1ª pasada | F24: No | G24: 10 | I24: =IF(H24="","",H24-G24) | J24: =IF(H24="","",MAX(0,N(J23)+G24-H24)) | K24: =IF(OR(H24="",G24=0),"",H24/G24) | L24: =IF(H24="","Pendiente",IF(J24>Resumen!$B$12,"Correr calendario",IF(H24>=G24,"Cumplida",IF(H24>=Resumen!$B$11,"Parcial","Bajo mínimo")))) -> Pendiente
A25: 21 | B25: =Resumen!$B$4+7*(A25-1) -> 46461 | C25: =B25+6 -> 46467 | D25: Portafolio | E25: 1ª pasada | F25: No | G25: 10 | I25: =IF(H25="","",H25-G25) | J25: =IF(H25="","",MAX(0,N(J24)+G25-H25)) | K25: =IF(OR(H25="",G25=0),"",H25/G25) | L25: =IF(H25="","Pendiente",IF(J25>Resumen!$B$12,"Correr calendario",IF(H25>=G25,"Cumplida",IF(H25>=Resumen!$B$11,"Parcial","Bajo mínimo")))) -> Pendiente
A26: 22 | B26: =Resumen!$B$4+7*(A26-1) -> 46468 | C26: =B26+6 -> 46474 | D26: Portafolio | E26: 1ª pasada | F26: No | G26: 10 | I26: =IF(H26="","",H26-G26) | J26: =IF(H26="","",MAX(0,N(J25)+G26-H26)) | K26: =IF(OR(H26="",G26=0),"",H26/G26) | L26: =IF(H26="","Pendiente",IF(J26>Resumen!$B$12,"Correr calendario",IF(H26>=G26,"Cumplida",IF(H26>=Resumen!$B$11,"Parcial","Bajo mínimo")))) -> Pendiente | M26: Fin: sáb 28-mar = decisión mayo o noviembre
A27: 23 | B27: =Resumen!$B$4+7*(A27-1) -> 46475 | C27: =B27+6 -> 46481 | D27: Todos | E27: 2ª pasada + QBank mixto | F27: No | G27: 10 | I27: =IF(H27="","",H27-G27) | J27: =IF(H27="","",MAX(0,N(J26)+G27-H27)) | K27: =IF(OR(H27="",G27=0),"",H27/G27) | L27: =IF(H27="","Pendiente",IF(J27>Resumen!$B$12,"Correr calendario",IF(H27>=G27,"Cumplida",IF(H27>=Resumen!$B$11,"Parcial","Bajo mínimo")))) -> Pendiente
A28: 24 | B28: =Resumen!$B$4+7*(A28-1) -> 46482 | C28: =B28+6 -> 46488 | D28: Todos | E28: 2ª pasada + QBank mixto | F28: No | G28: 10 | I28: =IF(H28="","",H28-G28) | J28: =IF(H28="","",MAX(0,N(J27)+G28-H28)) | K28: =IF(OR(H28="",G28=0),"",H28/G28) | L28: =IF(H28="","Pendiente",IF(J28>Resumen!$B$12,"Correr calendario",IF(H28>=G28,"Cumplida",IF(H28>=Resumen!$B$11,"Parcial","Bajo mínimo")))) -> Pendiente | M28: Vie 2-abr feriado Semana Santa (confirmar): bloque extra posible
A29: 25 | B29: =Resumen!$B$4+7*(A29-1) -> 46489 | C29: =B29+6 -> 46495 | D29: Todos | E29: Mock 1 + análisis | F29: No | G29: 10 | I29: =IF(H29="","",H29-G29) | J29: =IF(H29="","",MAX(0,N(J28)+G29-H29)) | K29: =IF(OR(H29="",G29=0),"",H29/G29) | L29: =IF(H29="","Pendiente",IF(J29>Resumen!$B$12,"Correr calendario",IF(H29>=G29,"Cumplida",IF(H29>=Resumen!$B$11,"Parcial","Bajo mínimo")))) -> Pendiente
A30: 26 | B30: =Resumen!$B$4+7*(A30-1) -> 46496 | C30: =B30+6 -> 46502 | D30: Todos | E30: Mock 2 + análisis | F30: No | G30: 10 | I30: =IF(H30="","",H30-G30) | J30: =IF(H30="","",MAX(0,N(J29)+G30-H30)) | K30: =IF(OR(H30="",G30=0),"",H30/G30) | L30: =IF(H30="","Pendiente",IF(J30>Resumen!$B$12,"Correr calendario",IF(H30>=G30,"Cumplida",IF(H30>=Resumen!$B$11,"Parcial","Bajo mínimo")))) -> Pendiente
A31: 27 | B31: =Resumen!$B$4+7*(A31-1) -> 46503 | C31: =B31+6 -> 46509 | D31: Todos | E31: Mock 3 + análisis | F31: No | G31: 10 | I31: =IF(H31="","",H31-G31) | J31: =IF(H31="","",MAX(0,N(J30)+G31-H31)) | K31: =IF(OR(H31="",G31=0),"",H31/G31) | L31: =IF(H31="","Pendiente",IF(J31>Resumen!$B$12,"Correr calendario",IF(H31>=G31,"Cumplida",IF(H31>=Resumen!$B$11,"Parcial","Bajo mínimo")))) -> Pendiente
A32: 28 | B32: =Resumen!$B$4+7*(A32-1) -> 46510 | C32: =B32+6 -> 46516 | D32: Todos | E32: Repaso liviano, sin material nuevo | F32: No | G32: 7 | I32: =IF(H32="","",H32-G32) | J32: =IF(H32="","",MAX(0,N(J31)+G32-H32)) | K32: =IF(OR(H32="",G32=0),"",H32/G32) | L32: =IF(H32="","Pendiente",IF(J32>Resumen!$B$12,"Correr calendario",IF(H32>=G32,"Cumplida",IF(H32>=Resumen!$B$11,"Parcial","Bajo mínimo")))) -> Pendiente
A33: 29 | B33: =Resumen!$B$4+7*(A33-1) -> 46517 | C33: =B33+6 -> 46523 | D33: Examen | E33: Descanso + examen | F33: — | G33: 0 | I33: =IF(H33="","",H33-G33) | J33: =IF(H33="","",MAX(0,N(J32)+G33-H33)) | K33: =IF(OR(H33="",G33=0),"",H33/G33) | L33: =IF(H33="","Pendiente",IF(J33>Resumen!$B$12,"Correr calendario",IF(H33>=G33,"Cumplida",IF(H33>=Resumen!$B$11,"Parcial","Bajo mínimo")))) -> Pendiente | M33: Semana del examen (fecha por confirmar)
A35: Supuestos propios: semana 1 = 6 bloques por el cumpleaños; semanas 6, 7, 9 y 10 reducidas por matrimonios y fiestas; feriados y viaje de febrero por confirmar. Fechas del examen: por confirmar.

Sheet Temas
A1: Temas: plan y avance
A2: Avance por tema = 35% leído/subrayado + 20% resumen + 45% ejercicios. Desempeño L1 = lectura aproximada de tu gráfico de feb-2025.
A4: Tema | B4: Desempeño L1 | C4: Prioridad | D4: Horas plan | E4: Bloques | F4: Sem. inicio | G4: Sem. fin | H4: Fecha inicio | I4: Fecha fin | J4: Repaso L1 hecho | K4: Leído / subrayado % | L4: Resumen % | M4: QBank % | N4: Feynman | O4: Brechas | P4: Puntaje prom. registro | Q4: Avance
A5: Ética | B5: Alto | C5: Media | D5: 22 | E5: =ROUND(D5/Resumen!$B$14,0) -> 15 | F5: 1 | G5: 22 | H5: =Resumen!$B$4+7*(F5-1) -> 46321 | I5: =Resumen!$B$4+7*(G5-1)+6 -> 46474 | J5: No | K5: 0 | L5: 0 | M5: 0 | N5: No | O5: No | P5: =IFERROR(AVERAGEIFS(Registro!$D$6:$D$500,Registro!$C$6:$C$500,A5),"") | Q5: =0.35*K5+0.2*L5+0.45*M5 -> 0
A6: Quant | B6: Alto | C6: Normal | D6: 30 | E6: =ROUND(D6/Resumen!$B$14,0) -> 20 | F6: 1 | G6: 2 | H6: =Resumen!$B$4+7*(F6-1) -> 46321 | I6: =Resumen!$B$4+7*(G6-1)+6 -> 46334 | J6: No | K6: 0 | L6: 0 | M6: 0 | N6: No | O6: No | P6: =IFERROR(AVERAGEIFS(Registro!$D$6:$D$500,Registro!$C$6:$C$500,A6),"") | Q6: =0.35*K6+0.2*L6+0.45*M6 -> 0
A7: Economía | B7: Bajo (el más débil) | C7: Alta | D7: 28 | E7: =ROUND(D7/Resumen!$B$14,0) -> 19 | F7: 3 | G7: 4 | H7: =Resumen!$B$4+7*(F7-1) -> 46335 | I7: =Resumen!$B$4+7*(G7-1)+6 -> 46348 | J7: No | K7: 0 | L7: 0 | M7: 0 | N7: No | O7: No | P7: =IFERROR(AVERAGEIFS(Registro!$D$6:$D$500,Registro!$C$6:$C$500,A7),"") | Q7: =0.35*K7+0.2*L7+0.45*M7 -> 0
A8: FSA | B8: Alto | C8: Normal | D8: 48 | E8: =ROUND(D8/Resumen!$B$14,0) -> 32 | F8: 5 | G8: 7 | H8: =Resumen!$B$4+7*(F8-1) -> 46349 | I8: =Resumen!$B$4+7*(G8-1)+6 -> 46369 | J8: No | K8: 0 | L8: 0 | M8: 0 | N8: No | O8: No | P8: =IFERROR(AVERAGEIFS(Registro!$D$6:$D$500,Registro!$C$6:$C$500,A8),"") | Q8: =0.35*K8+0.2*L8+0.45*M8 -> 0
A9: Corporate Issuers | B9: Medio | C9: Media | D9: 22 | E9: =ROUND(D9/Resumen!$B$14,0) -> 15 | F9: 8 | G9: 9 | H9: =Resumen!$B$4+7*(F9-1) -> 46370 | I9: =Resumen!$B$4+7*(G9-1)+6 -> 46383 | J9: No | K9: 0 | L9: 0 | M9: 0 | N9: No | O9: No | P9: =IFERROR(AVERAGEIFS(Registro!$D$6:$D$500,Registro!$C$6:$C$500,A9),"") | Q9: =0.35*K9+0.2*L9+0.45*M9 -> 0
A10: Equity | B10: Alto | C10: Normal | D10: 48 | E10: =ROUND(D10/Resumen!$B$14,0) -> 32 | F10: 10 | G10: 12 | H10: =Resumen!$B$4+7*(F10-1) -> 46384 | I10: =Resumen!$B$4+7*(G10-1)+6 -> 46404 | J10: No | K10: 0 | L10: 0 | M10: 0 | N10: No | O10: No | P10: =IFERROR(AVERAGEIFS(Registro!$D$6:$D$500,Registro!$C$6:$C$500,A10),"") | Q10: =0.35*K10+0.2*L10+0.45*M10 -> 0
A11: Renta Fija | B11: Alto | C11: Normal | D11: 40 | E11: =ROUND(D11/Resumen!$B$14,0) -> 27 | F11: 13 | G11: 15 | H11: =Resumen!$B$4+7*(F11-1) -> 46405 | I11: =Resumen!$B$4+7*(G11-1)+6 -> 46425 | J11: No | K11: 0 | L11: 0 | M11: 0 | N11: No | O11: No | P11: =IFERROR(AVERAGEIFS(Registro!$D$6:$D$500,Registro!$C$6:$C$500,A11),"") | Q11: =0.35*K11+0.2*L11+0.45*M11 -> 0
A12: Derivados | B12: Muy alto | C12: Normal | D12: 22 | E12: =ROUND(D12/Resumen!$B$14,0) -> 15 | F12: 16 | G12: 17 | H12: =Resumen!$B$4+7*(F12-1) -> 46426 | I12: =Resumen!$B$4+7*(G12-1)+6 -> 46439 | J12: No | K12: 0 | L12: 0 | M12: 0 | N12: No | O12: No | P12: =IFERROR(AVERAGEIFS(Registro!$D$6:$D$500,Registro!$C$6:$C$500,A12),"") | Q12: =0.35*K12+0.2*L12+0.45*M12 -> 0
A13: Alternativos | B13: Alto | C13: Normal | D13: 20 | E13: =ROUND(D13/Resumen!$B$14,0) -> 13 | F13: 18 | G13: 19 | H13: =Resumen!$B$4+7*(F13-1) -> 46440 | I13: =Resumen!$B$4+7*(G13-1)+6 -> 46453 | J13: No | K13: 0 | L13: 0 | M13: 0 | N13: No | O13: No | P13: =IFERROR(AVERAGEIFS(Registro!$D$6:$D$500,Registro!$C$6:$C$500,A13),"") | Q13: =0.35*K13+0.2*L13+0.45*M13 -> 0
A14: Portafolio | B14: Medio | C14: Media | D14: 36 | E14: =ROUND(D14/Resumen!$B$14,0) -> 24 | F14: 20 | G14: 22 | H14: =Resumen!$B$4+7*(F14-1) -> 46454 | I14: =Resumen!$B$4+7*(G14-1)+6 -> 46474 | J14: No | K14: 0 | L14: 0 | M14: 0 | N14: No | O14: No | P14: =IFERROR(AVERAGEIFS(Registro!$D$6:$D$500,Registro!$C$6:$C$500,A14),"") | Q14: =0.35*K14+0.2*L14+0.45*M14 -> 0
A15: Total | D15: =SUM(D5:D14) -> 316 | E15: =SUM(E5:E14) -> 212 | Q15: =AVERAGE(Q5:Q14) -> 0
A17: Ética va en goteo de 1 h/semana (semanas 1–22) y se refuerza en la fase final. Horas por tema son supuestos míos (Economía +, Derivados −); ajústalos.

Sheet Registro
A1: Registro de ejercicios y mocks
A2: La fila 5 es un ejemplo (se ignora: bórrala o sobrescríbela). Los promedios por tema van a la hoja Temas.
A4: Fecha | B4: Tipo | C4: Tema | D4: Puntaje % | E4: Nº preguntas | F4: Notas
A5: 46338 | B5: QBank | C5: Economía | D5: 0.55 | E5: 20 | F5: EJEMPLO: fallé monetary/fiscal; pasa al registro de errores

Sheet Errores
A1: Registro de errores (tu 'Secret Sauce' personal)
A2: Cada error = 1 fila. Repasar a los 7 y a los 21 días. La fila 5 es un ejemplo.
A4: Fecha | B4: Tema | C4: Concepto / LOS | D4: Qué respondí | E4: Tipo de error | F4: Regla correcta | G4: Repaso 1 (+7d) | H4: Repaso 2 (+21d)
A5: 46338 | B5: Economía | C5: Política fiscal vs monetaria | D5: Elegí la tasa de interés como herramienta fiscal | E5: Concepto | F5: La fiscal usa gasto e impuestos; la monetaria, tasa y reservas (ejemplo) | G5: 46345 | H5: 46359

Sheet Semana actual
A1: Semana actual: lo que planeaste vs lo que hiciste
A2: Si algo se cae, cambia el plan del día y escribe en 'Mover a' dónde recuperas el bloque (o avísame y reacomodo).
A3: Lunes de la semana: | B3: =Resumen!B4+7*(Resumen!B7-1) -> 46321 | C3: Se calcula solo desde el panel; sobrescríbela para revisar otra semana.
A5: Día | B5: Fecha | C5: Franja | D5: Bloque(s) plan | E5: Plan | F5: Hecho | G5: Tramos transporte (0–2) | H5: Mover a (día) | I5: Nota
A6: Lunes | B6: =$B$3+0 -> 46321 | C6: 20:00–21:30 | D6: R | E6: 1 | F6: 0 | G6: 0
A7: Martes | B7: =$B$3+1 -> 46322 | C7: 20:00–21:30 | D7: R | E7: 1 | F7: 0 | G7: 0
A8: Miércoles | B8: =$B$3+2 -> 46323 | C8: 20:00–21:30 | D8: Q | E8: 1 | F8: 0 | G8: 0
A9: Jueves | B9: =$B$3+3 -> 46324 | C9: 20:00–21:30 | D9: Q | E9: 1 | F9: 0 | G9: 0
A10: Viernes | B10: =$B$3+4 -> 46325 | C10: 15:00–18:30 | D10: L + Q | E10: 2 | F10: 0 | G10: 0
A11: Sábado | B11: =$B$3+5 -> 46326 | C11: 09:00–12:00 | D11: L + R | E11: 2 | F11: 0 | G11: 0
A12: Domingo | B12: =$B$3+6 -> 46327 | C12: 16:00–19:30 | D12: V + F | E12: 2 | F12: 0 | G12: 0
A14: Totales | E14: =SUM(E6:E12) -> 10 | F14: =SUM(F6:F12) -> 0 | G14: =SUM(G6:G12) -> 0
A16: Plan en Calendario para esta semana | E16: =INDEX(Calendario!$G$5:$G$33,Resumen!B7) -> 6
A17: Cumplimiento de la semana | E17: =IF(E14=0,"",F14/E14) -> 0

Sheet Reglas
A1: Perfil, método y reglas de reacomodo
A3: PERFIL (dato tuyo)
B4: Ingeniería Comercial UC, FP&A en aseguradora de vida. Nivel 1 aprobado feb-2025 (1710 vs MPS 1600). Vives con tus padres. Polola: vie noche a dom mediodía.
B5: Trabajo L–J 8:00–17:30, Vie hasta 14:00. Transporte sentado, puedes leer. Mejor estudiar tras una pausa de comida. Samexid con conocimiento de tu médico.
B6: Material: Schweser impresos (2025 o 2026), mocks oficiales descargados, calculadora BA II Plus. Aprendes mejor escribiendo, leyendo y viendo ejercicios resueltos.
A7: MÉTODO POR TEMA
B8: 1) Repaso L1 con tu propio resumen (1 bloque). 2) Leer y subrayar (transporte). 3) Resumir lo subrayado. 4) Ejercicios y registro de errores. 5) Feynman + detector de brechas al cerrar.
A9: REGLAS
A10: 1 | B10: Avísame qué día u horas se caen y cuáles quedan libres; reordeno la semana.
A11: 2 | B11: Bloque perdido = deuda. Orden de sacrificio: Ética, Feynman/brechas, repaso, resumen más corto. El núcleo (leer y ejercicios) no se sacrifica.
A12: 3 | B12: Máx. 2 bloques en un día de semana. Hasta 3 en fin de semana.
A13: 4 | B13: Recuperas hasta 3 bloques de deuda por semana; el resto va a las semanas colchón (9, 12, 15, 19).
A14: 5 | B14: Deuda > 6 bloques: corre el calendario 1 semana. Corrimiento > 2 semanas antes del 28-mar: se evalúa pasar a noviembre.
A15: 6 | B15: Semana con menos de 7 bloques: solo núcleo y errores. Mala noche o enfermedad: se salta, no se compensa ese mismo día.
A16: 7 | B16: Decisión mayo/noviembre el 28-mar: ≥ 65–70% en QBank y 10 temas vistos = mayo.
